dokker/__init__.py
dokker/builders.py
dokker/cli.py
dokker/command.py
dokker/compose_spec.py
dokker/deployment.py
dokker/errors.py
dokker/log_watcher.py
dokker/project.py
dokker/py.typed
dokker/types.py
dokker/loggers/__init__.py
dokker/loggers/print.py
dokker/loggers/void.py
dokker/projects/__init__.py
dokker/projects/copy.py
dokker/projects/dokker.py
dokker/projects/errors.py
dokker/projects/local.py
dokker-2.3.0.dist-info/METADATA
dokker-2.3.0.dist-info/WHEEL
dokker-2.3.0.dist-info/RECORD
