Metadata-Version: 2.4
Name: dokker
Version: 2.3.0
Author-email: jhnnsrs <jhnnsrs@gmail.com>
Requires-Python: >=3.11
Requires-Dist: aiohttp<4,>=3.9.1
Requires-Dist: certifi>=2023.11.17
Requires-Dist: koil>=2.0.4
Requires-Dist: pydantic>2
